mne_pipeline_hd/__init__.py
mne_pipeline_hd/__main__.py
mne_pipeline_hd/conftest.py
mne_pipeline_hd/pytest.ini
mne_pipeline_hd/development/Makefile
mne_pipeline_hd/development/__init__.py
mne_pipeline_hd/development/check_ressources.py
mne_pipeline_hd/development/console_widget_speed.py
mne_pipeline_hd/development/dev_utils.py
mne_pipeline_hd/development/development_considerations.md
mne_pipeline_hd/extra/__init__.py
mne_pipeline_hd/extra/color_themes.json
mne_pipeline_hd/extra/default_settings.json
mne_pipeline_hd/extra/functions.csv
mne_pipeline_hd/extra/license.txt
mne_pipeline_hd/extra/mne_license.txt
mne_pipeline_hd/extra/mne_pipeline_icon_dark.png
mne_pipeline_hd/extra/mne_pipeline_icon_light.png
mne_pipeline_hd/extra/mne_pipeline_logo_evee_smaller.jpg
mne_pipeline_hd/extra/parameters.csv
mne_pipeline_hd/functions/__init__.py
mne_pipeline_hd/functions/operations.py
mne_pipeline_hd/functions/plot.py
mne_pipeline_hd/gui/__init__.py
mne_pipeline_hd/gui/base_widgets.py
mne_pipeline_hd/gui/dialogs.py
mne_pipeline_hd/gui/education_widgets.py
mne_pipeline_hd/gui/function_widgets.py
mne_pipeline_hd/gui/gui_utils.py
mne_pipeline_hd/gui/loading_widgets.py
mne_pipeline_hd/gui/main_window.py
mne_pipeline_hd/gui/models.py
mne_pipeline_hd/gui/parameter_widgets.py
mne_pipeline_hd/gui/plot_widgets.py
mne_pipeline_hd/gui/tools.py
mne_pipeline_hd/gui/welcome_window.py
mne_pipeline_hd/pipeline/__init__.py
mne_pipeline_hd/pipeline/controller.py
mne_pipeline_hd/pipeline/function_utils.py
mne_pipeline_hd/pipeline/legacy.py
mne_pipeline_hd/pipeline/loading.py
mne_pipeline_hd/pipeline/parallel.py
mne_pipeline_hd/pipeline/pipeline_utils.py
mne_pipeline_hd/pipeline/plot_utils.py
mne_pipeline_hd/pipeline/project.py
mne_pipeline_hd/tests/__init__.py
mne_pipeline_hd/tests/_test_utils.py
mne_pipeline_hd/tests/test_app.py
mne_pipeline_hd/tests/test_base_widgets.py
mne_pipeline_hd/tests/test_concurrent.py
mne_pipeline_hd/tests/test_console.py
mne_pipeline_hd/tests/test_controller.py
mne_pipeline_hd-0.3.5.dist-info/METADATA
mne_pipeline_hd-0.3.5.dist-info/WHEEL
mne_pipeline_hd-0.3.5.dist-info/entry_points.txt
mne_pipeline_hd-0.3.5.dist-info/licenses/LICENSE
mne_pipeline_hd-0.3.5.dist-info/RECORD
