Metadata-Version: 2.3
Name: mne-pipeline-hd
Version: 0.3.5
Summary: A Pipeline-GUI for MNE-Python from MEG-Lab Heidelberg
Project-URL: Homepage, https://github.com/marsipu/mne-pipeline-hd
Project-URL: Repository, https://github.com/marsipu/mne-pipeline-hd.git
Author-email: "Martin G. Schulz" <dev@mgschulz.de>
License: BSD 3-Clause License
License-File: LICENSE
Keywords: eeg,gui,heidelberg,meg,mne-python,pipeline
Classifier: Intended Audience :: Science/Research
Classifier: License :: OSI Approved :: BSD License
Classifier: Operating System :: OS Independent
Classifier: Programming Language :: Python
Classifier: Topic :: Scientific/Engineering
Requires-Python: >=3.9
Requires-Dist: autoreject
Requires-Dist: darkdetect
Requires-Dist: h5io
Requires-Dist: h5netcdf
Requires-Dist: mne
Requires-Dist: mne-connectivity
Requires-Dist: mne-qt-browser
Requires-Dist: nibabel
Requires-Dist: psutil
Requires-Dist: pyobjc-framework-cocoa; sys_platform == 'Darwin'
Requires-Dist: pyvistaqt
Requires-Dist: qtpy
Requires-Dist: vtk
Provides-Extra: docs
Requires-Dist: pydata-sphinx-theme; extra == 'docs'
Requires-Dist: sphinx; extra == 'docs'
Provides-Extra: tests
Requires-Dist: black; extra == 'tests'
Requires-Dist: pre-commit; extra == 'tests'
Requires-Dist: pytest; extra == 'tests'
Requires-Dist: pytest-qt; extra == 'tests'
Requires-Dist: ruff; extra == 'tests'
